examples/__init__.py
examples/using_cv_benchmarks.py
examples/using_cv_explainers.py
examples/using_rise_plus.py
examples/using_tabsim.py
examples/using_tabular_explainers.py
examples/common/__init__.py
examples/common/dataset.py
examples/common/resnet.py
mindspore_xai/__init__.py
mindspore_xai/_version.py
mindspore_xai/benchmark/__init__.py
mindspore_xai/benchmark/class_sensitivity.py
mindspore_xai/benchmark/faithfulness.py
mindspore_xai/benchmark/localization.py
mindspore_xai/benchmark/metric.py
mindspore_xai/benchmark/robustness.py
mindspore_xai/common/__init__.py
mindspore_xai/common/attribution.py
mindspore_xai/common/operators.py
mindspore_xai/common/utils.py
mindspore_xai/explainer/__init__.py
mindspore_xai/explainer/backprop/__init__.py
mindspore_xai/explainer/backprop/backprop_utils.py
mindspore_xai/explainer/backprop/gradcam.py
mindspore_xai/explainer/backprop/gradient.py
mindspore_xai/explainer/backprop/intermediate_layer.py
mindspore_xai/explainer/backprop/modified_relu.py
mindspore_xai/explainer/perturb/__init__.py
mindspore_xai/explainer/perturb/ablation.py
mindspore_xai/explainer/perturb/lime.py
mindspore_xai/explainer/perturb/occlusion.py
mindspore_xai/explainer/perturb/perturbation.py
mindspore_xai/explainer/perturb/replacement.py
mindspore_xai/explainer/perturb/rise.py
mindspore_xai/explainer/perturb/riseplus.py
mindspore_xai/explainer/shap/__init__.py
mindspore_xai/explainer/shap/gradient.py
mindspore_xai/explainer/shap/kernel.py
mindspore_xai/explainer/shap/shap.py
mindspore_xai/third_party/__init__.py
mindspore_xai/third_party/lime/__init__.py
mindspore_xai/third_party/lime/lime/__init__.py
mindspore_xai/third_party/lime/lime/bundle.js
mindspore_xai/third_party/lime/lime/discretize.py
mindspore_xai/third_party/lime/lime/explanation.py
mindspore_xai/third_party/lime/lime/lime_base.py
mindspore_xai/third_party/lime/lime/lime_tabular.py
mindspore_xai/third_party/shap/__init__.py
mindspore_xai/third_party/shap/shap/__init__.py
mindspore_xai-1.8.1.dist-info/LICENSE
mindspore_xai-1.8.1.dist-info/METADATA
mindspore_xai-1.8.1.dist-info/NOTICE
mindspore_xai-1.8.1.dist-info/WHEEL
mindspore_xai-1.8.1.dist-info/entry_points.txt
mindspore_xai-1.8.1.dist-info/top_level.txt
mindspore_xai-1.8.1.dist-info/RECORD
